transkribus_fixer/__init__.py
transkribus_fixer/cli.py
transkribus_fixer/fixer.py
transkribus_fixer-0.0.1.dist-info/DESCRIPTION.rst
transkribus_fixer-0.0.1.dist-info/METADATA
transkribus_fixer-0.0.1.dist-info/RECORD
transkribus_fixer-0.0.1.dist-info/WHEEL
transkribus_fixer-0.0.1.dist-info/entry_points.txt
transkribus_fixer-0.0.1.dist-info/metadata.json
transkribus_fixer-0.0.1.dist-info/top_level.txt
