Metadata-Version: 2.0
Name: transkribus-fixer
Version: 0.0.1
Summary: UNKNOWN
Home-page: https://github.com/kba/transkribus-fixer
Author: kba
Author-email: unixprog@gmail.com
License: Apache License 2.0
Platform: UNKNOWN
Requires-Dist: click
Requires-Dist: lxml
